README.md
setup.py
bin/beanstalk_cleaner
bin/build_docker_base_image
bin/build_docker_image
bin/deploy_pipeline
bin/eb_deploy
bin/get_deploy_config_path
bin/get_live_environment
bin/print_version
klue_deploy_configs/Dockerfile.base.template
klue_deploy_configs/Dockerfile.template
klue_deploy_configs/Dockerrun.aws.json.template
klue_deploy_configs/__init__.py
klue_deploy_configs/autoscaling.config
klue_deploy_configs/aws-secrets.config
klue_deploy_configs/healthcheckurl.config
klue_deploy_configs/notifications.config
klue_deploy_configs/rolling-updates.config
klue_microservice_deploy.egg-info/PKG-INFO
klue_microservice_deploy.egg-info/SOURCES.txt
klue_microservice_deploy.egg-info/dependency_links.txt
klue_microservice_deploy.egg-info/not-zip-safe
klue_microservice_deploy.egg-info/requires.txt
klue_microservice_deploy.egg-info/top_level.txt
test/test_pep8.py