Metadata-Version: 1.1
Name: klue-microservice-deploy
Version: 0.0.62
Summary: Tools to run a Klue micro-service on Amazon aws/docker
Home-page: https://github.com/erwan-lemonnier/klue-microservice-deploy
Author: Erwan Lemonnier
Author-email: erwan@lemonnier.se
License: BSD
Platform: any
Classifier: Environment :: Web Environment
Classifier: Intended Audience :: Developers
Classifier: License :: OSI Approved :: BSD License
Classifier: Operating System :: OS Independent
Classifier: Programming Language :: Python
Classifier: Topic :: Internet :: WWW/HTTP :: Dynamic Content
Classifier: Topic :: Software Development :: Libraries :: Python Modules
